{
  "looting": {
    "items": [

    ],
    "maxDanger": 10,
    "minCapacity": 100,
    "containers": [

    ],
    "everyItem": false
  },
  "targeting": [
    {
      "useSpellAttack": false,
      "useRuneAttack": false,
      "minMana": 200,
      "avoidAttacks": false,
      "attackSpellDelay": 2500,
      "groupAttackSpell": "",
      "danger": 1,
      "runeAttackDelay": 2000,
      "lureCavebot": true,
      "dontLoot": false,
      "useGroupAttackRune": false,
      "groupRuneAttackRadius": 1,
      "groupAttackIgnorePlayers": false,
      "maxDistance": 10,
      "groupAttackIgnoreParty": false,
      "lureCount": 3,
      "useGroupAttack": false,
      "groupRuneAttackTargets": 2,
      "attackSpell": "",
      "chase": false,
      "priority": 1,
      "keepDistanceRange": 1,
      "keepDistance": false,
      "groupAttackTargets": 2,
      "groupAttackRune": 0,
      "groupAttackRadius": 1,
      "groupRuneAttackDelay": 5000,
      "lure": false,
      "attackRune": 0,
      "groupAttackDelay": 5000,
      "minManaGroup": 1500,
      "name": "Zetsu V",
      "regex": "^zetsu v$"
    },
    {
      "useSpellAttack": false,
      "useRuneAttack": false,
      "minMana": 200,
      "avoidAttacks": false,
      "groupAttackTargets": 2,
      "groupAttackSpell": "",
      "danger": 1,
      "runeAttackDelay": 2000,
      "lureCavebot": false,
      "dontLoot": false,
      "useGroupAttackRune": false,
      "groupRuneAttackRadius": 1,
      "groupAttackIgnorePlayers": false,
      "maxDistance": 10,
      "groupAttackIgnoreParty": false,
      "lureCount": 0,
      "useGroupAttack": false,
      "groupRuneAttackTargets": 2,
      "attackSpell": "",
      "groupAttackRune": 0,
      "groupAttackRadius": 1,
      "keepDistanceRange": 1,
      "groupRuneAttackDelay": 5000,
      "priority": 1,
      "attackRune": 0,
      "groupAttackDelay": 5000,
      "minManaGroup": 1500,
      "lure": false,
      "keepDistance": false,
      "attackSpellDelay": 2500,
      "chase": false,
      "name": "Gedou Monster",
      "regex": "^gedou monster$"
    }
  ]
}